nilvec-0.1.8.dist-info/METADATA
nilvec-0.1.8.dist-info/WHEEL
nilvec/__init__.py
nilvec/__init__.pyi
nilvec/py.typed
nilvec/nilvec.cpython-312-darwin.so
nilvec-0.1.8.dist-info/RECORD
