Metadata-Version: 2.4
Name: nilvec
Version: 0.1.8
Classifier: Programming Language :: Rust
Classifier: Programming Language :: Python :: Implementation :: CPython
Classifier: Programming Language :: Python :: Implementation :: PyPy
Summary: A lightweight library for nearest neighbor search in Rust.
Author-email: Collin Drake <collinlindendrake@gmail.com>
Maintainer-email: Collin Drake <collinlindendrake@gmail.com>
License: MIT
Requires-Python: >=3.8
Project-URL: Source Code, https://github.com/cldrake01/NilVec
